{
    "blockhash0" : {
         "env" : {
             "previousHash" : "5e20a0453cecd065ea59c37ac63e079ee08998b6045136a8ce6635c7912ec0b6",
             "currentNumber" : "5",
             "currentGasLimit" : "1000000",
             "currentDifficulty" : "256",
             "currentTimestamp" : 1,
             "currentCoinbase" : "2adc25665018aa1fe0e6bc666dac8fc2697ff9ba"
         },
         "pre" : {
             "095e7baea6a6c7c4c2dfeb977efac326af552d87" : {
                 "balance" : "1000000000000000000",
                 "nonce" : "0",
                 "code" : "{ [[ 0 ]] (BLOCKHASH 0) [[ 1 ]] (BLOCKHASH 5) [[ 2 ]] (BLOCKHASH 4) }",
                 "storage": {}
             },
             "a94f5374fce5edbc8e2a8697c15331677e6ebf0b" : {
                 "balance" : "100000",
                 "nonce" : "0",
                 "code" : "",
                 "storage": {}
             }
         },
         "transaction" : {
             "nonce" : "0",
             "gasPrice" : "1",
             "gasLimit" : "8500",
             "to" : "095e7baea6a6c7c4c2dfeb977efac326af552d87",
             "value" : "10",
             "secretKey" : "45a915e4d060149eb4365960e6a7a45f334393093061116b197e3240065ff2d8",
             "data" : ""
         }
     },

    "blockhashOutOfRange" : {
         "env" : {
             "previousHash" : "5e20a0453cecd065ea59c37ac63e079ee08998b6045136a8ce6635c7912ec0b6",
             "currentNumber" : "257",
             "currentGasLimit" : "1000000",
             "currentDifficulty" : "256",
             "currentTimestamp" : 1,
             "currentCoinbase" : "2adc25665018aa1fe0e6bc666dac8fc2697ff9ba"
         },
         "pre" : {
             "095e7baea6a6c7c4c2dfeb977efac326af552d87" : {
                 "balance" : "1000000000000000000",
                 "nonce" : "0",
                 "code" : "{ [[ 0 ]] (BLOCKHASH 0) [[ 1 ]] (BLOCKHASH 257) [[ 2 ]] (BLOCKHASH 0xffffffffffffffffffffffffffffffffffffffffffffffffffffffffffffffff) }",
                 "storage": {}
             },
             "a94f5374fce5edbc8e2a8697c15331677e6ebf0b" : {
                 "balance" : "100000",
                 "nonce" : "0",
                 "code" : "",
                 "storage": {}
             }
         },
         "transaction" : {
             "nonce" : "0",
             "gasPrice" : "1",
             "gasLimit" : "8500",
             "to" : "095e7baea6a6c7c4c2dfeb977efac326af552d87",
             "value" : "10",
             "secretKey" : "45a915e4d060149eb4365960e6a7a45f334393093061116b197e3240065ff2d8",
             "data" : ""
         }
     },

    "blockhashInRange" : {
         "env" : {
             "previousHash" : "5e20a0453cecd065ea59c37ac63e079ee08998b6045136a8ce6635c7912ec0b6",
             "currentNumber" : "257",
             "currentGasLimit" : "1000000",
             "currentDifficulty" : "256",
             "currentTimestamp" : 1,
             "currentCoinbase" : "2adc25665018aa1fe0e6bc666dac8fc2697ff9ba"
         },
         "pre" : {
             "095e7baea6a6c7c4c2dfeb977efac326af552d87" : {
                 "balance" : "1000000000000000000",
                 "nonce" : "0",
                 "code" : "{ [[ 0 ]] (BLOCKHASH 1) [[ 1 ]] (BLOCKHASH 2) [[ 2 ]] (BLOCKHASH 256) }",
                 "storage": {}
             },
             "a94f5374fce5edbc8e2a8697c15331677e6ebf0b" : {
                 "balance" : "100000",
                 "nonce" : "0",
                 "code" : "",
                 "storage": {}
             }
         },
         "transaction" : {
             "nonce" : "0",
             "gasPrice" : "1",
             "gasLimit" : "8500",
             "to" : "095e7baea6a6c7c4c2dfeb977efac326af552d87",
             "value" : "10",
             "secretKey" : "45a915e4d060149eb4365960e6a7a45f334393093061116b197e3240065ff2d8",
             "data" : ""
         }
     }
}
